devheronpy/__init__.py
devheronpy/dsl/__init__.py
devheronpy/spouts/__init__.py
devheronpy-0.0.8.dist-info/DESCRIPTION.rst
devheronpy-0.0.8.dist-info/METADATA
devheronpy-0.0.8.dist-info/RECORD
devheronpy-0.0.8.dist-info/WHEEL
devheronpy-0.0.8.dist-info/metadata.json
devheronpy-0.0.8.dist-info/top_level.txt
heron/__init__.py
heron/api/__init__.py
heron/api/src/__init__.py
heron/api/src/python/__init__.py
heron/api/src/python/api_constants.py
heron/api/src/python/cloudpickle.py
heron/api/src/python/custom_grouping.py
heron/api/src/python/global_metrics.py
heron/api/src/python/metrics.py
heron/api/src/python/serializer.py
heron/api/src/python/stream.py
heron/api/src/python/task_hook.py
heron/api/src/python/topology.py
heron/api/src/python/topology_context.py
heron/api/src/python/tuple.py
heron/api/src/python/bolt/__init__.py
heron/api/src/python/bolt/base_bolt.py
heron/api/src/python/bolt/bolt.py
heron/api/src/python/bolt/window_bolt.py
heron/api/src/python/component/__init__.py
heron/api/src/python/component/base_component.py
heron/api/src/python/component/component_spec.py
heron/api/src/python/spout/__init__.py
heron/api/src/python/spout/base_spout.py
heron/api/src/python/spout/spout.py
heron/api/src/python/state/__init__.py
heron/api/src/python/state/state.py
heron/api/src/python/state/stateful_component.py
heron/dsl/__init__.py
heron/dsl/src/__init__.py
heron/dsl/src/python/__init__.py
heron/dsl/src/python/filterbolt.py
heron/dsl/src/python/flatmapbolt.py
heron/dsl/src/python/joinbolt.py
heron/dsl/src/python/mapbolt.py
heron/dsl/src/python/operation.py
heron/dsl/src/python/reducebykeyandwindowbolt.py
heron/dsl/src/python/repartitionbolt.py
heron/dsl/src/python/samplebolt.py
heron/dsl/src/python/streamlet.py
heron/proto/__init__.py
heron/proto/ckptmgr_pb2.py
heron/proto/common_pb2.py
heron/proto/execution_state_pb2.py
heron/proto/metrics_pb2.py
heron/proto/packing_plan_pb2.py
heron/proto/physical_plan_pb2.py
heron/proto/scheduler_pb2.py
heron/proto/stats_pb2.py
heron/proto/stmgr_pb2.py
heron/proto/tmaster_pb2.py
heron/proto/topology_pb2.py
heron/proto/tuple_pb2.py
heron/spouts/__init__.py
heron/spouts/src/__init__.py
