Metadata-Version: 2.0
Name: devheronpy
Version: 0.0.8
Summary: Python Topology API for Heron
Home-page: https://github.com/twitter/heron
Author: Heron Team
Author-email: heronstreaming@gmail.com
License: UNKNOWN
Keywords: heron topology python
Platform: UNKNOWN
Classifier: Development Status :: 3 - Alpha
Classifier: Intended Audience :: Developers
Classifier: Programming Language :: Python :: 2.7
Requires-Dist: protobuf (>=2.5.0,<3)
